{
  "openapi": "3.0.0",
  "info": {
    "title": "Collaborative Task Management API",
    "description": "RESTful API for the Collaborative Task Management Platform",
    "version": "1.0.0",
    "contact": {
      "name": "API Support",
      "email": "api-support@taskmanagement.com"
    },
    "license": {
      "name": "MIT",
      "url": "https://opensource.org/licenses/MIT"
    }
  },
  "servers": [
    {
      "url": "http://localhost:3000/api",
      "description": "Development server"
    },
    {
      "url": "https://api.taskmanagement.com",
      "description": "Production server"
    }
  ],
  "paths": {
    "/auth/register": {
      "post": {
        "summary": "Register a new user",
        "tags": ["Authentication"],
        "requestBody": {
          "required": true,
          "content": {
            "application/json": {
              "schema": {
                "type": "object",
                "required": ["email", "password", "name"],
                "properties": {
                  "email": {
                    "type": "string",
                    "format": "email",
                    "description": "User's email address"
                  },
                  "password": {
                    "type": "string",
                    "minLength": 8,
                    "description": "User's password (min 8 characters)"
                  },
                  "name": {
                    "type": "string",
                    "minLength": 1,
                    "description": "User's full name"
                  }
                }
              }
            }
          }
        },
        "responses": {
          "201": {
            "description": "User registered successfully",
            "content": {
              "application/json": {
                "schema": {
                  "type": "object",
                  "properties": {
                    "user": {
                      "$ref": "#/components/schemas/User"
                    },
                    "message": {
                      "type": "string"
                    }
                  }
                }
              }
            }
          },
          "400": {
            "$ref": "#/components/responses/BadRequest"
          },
          "409": {
            "$ref": "#/components/responses/Conflict"
          }
        }
      }
    },
    "/auth/login": {
      "post": {
        "summary": "Authenticate user",
        "tags": ["Authentication"],
        "requestBody": {
          "required": true,
          "content": {
            "application/json": {
              "schema": {
                "type": "object",
                "required": ["email", "password"],
                "properties": {
                  "email": {
                    "type": "string",
                    "format": "email"
                  },
                  "password": {
                    "type": "string"
                  }
                }
              }
            }
          }
        },
        "responses": {
          "200": {
            "description": "Authentication successful",
            "content": {
              "application/json": {
                "schema": {
                  "type": "object",
                  "properties": {
                    "user": {
                      "$ref": "#/components/schemas/User"
                    },
                    "token": {
                      "type": "string"
                    }
                  }
                }
              }
            }
          },
          "401": {
            "$ref": "#/components/responses/Unauthorized"
          }
        }
      }
    },
    "/projects": {
      "get": {
        "summary": "List projects",
        "tags": ["Projects"],
        "security": [{"BearerAuth": []}],
        "parameters": [
          {
            "name": "organization_id",
            "in": "query",
            "schema": {
              "type": "string",
              "format": "uuid"
            }
          },
          {
            "name": "status",
            "in": "query",
            "schema": {
              "type": "string",
              "enum": ["active", "archived", "completed"]
            }
          },
          {
            "name": "page",
            "in": "query",
            "schema": {
              "type": "integer",
              "minimum": 1,
              "default": 1
            }
          },
          {
            "name": "limit",
            "in": "query",
            "schema": {
              "type": "integer",
              "minimum": 1,
              "maximum": 100,
              "default": 20
            }
          }
        ],
        "responses": {
          "200": {
            "description": "Projects retrieved successfully",
            "content": {
              "application/json": {
                "schema": {
                  "type": "object",
                  "properties": {
                    "projects": {
                      "type": "array",
                      "items": {
                        "$ref": "#/components/schemas/Project"
                      }
                    },
                    "pagination": {
                      "$ref": "#/components/schemas/Pagination"
                    }
                  }
                }
              }
            }
          }
        }
      },
      "post": {
        "summary": "Create a new project",
        "tags": ["Projects"],
        "security": [{"BearerAuth": []}],
        "requestBody": {
          "required": true,
          "content": {
            "application/json": {
              "schema": {
                "type": "object",
                "required": ["name", "organization_id"],
                "properties": {
                  "name": {
                    "type": "string",
                    "minLength": 1
                  },
                  "description": {
                    "type": "string"
                  },
                  "organization_id": {
                    "type": "string",
                    "format": "uuid"
                  },
                  "visibility": {
                    "type": "string",
                    "enum": ["private", "public", "internal"],
                    "default": "private"
                  },
                  "color": {
                    "type": "string",
                    "pattern": "^#[0-9A-Fa-f]{6}$"
                  },
                  "start_date": {
                    "type": "string",
                    "format": "date"
                  },
                  "due_date": {
                    "type": "string",
                    "format": "date"
                  }
                }
              }
            }
          }
        },
        "responses": {
          "201": {
            "description": "Project created successfully",
            "content": {
              "application/json": {
                "schema": {
                  "$ref": "#/components/schemas/Project"
                }
              }
            }
          },
          "400": {
            "$ref": "#/components/responses/BadRequest"
          }
        }
      }
    },
    "/projects/{projectId}": {
      "get": {
        "summary": "Get project details",
        "tags": ["Projects"],
        "security": [{"BearerAuth": []}],
        "parameters": [
          {
            "name": "projectId",
            "in": "path",
            "required": true,
            "schema": {
              "type": "string",
              "format": "uuid"
            }
          }
        ],
        "responses": {
          "200": {
            "description": "Project retrieved successfully",
            "content": {
              "application/json": {
                "schema": {
                  "$ref": "#/components/schemas/Project"
                }
              }
            }
          },
          "404": {
            "$ref": "#/components/responses/NotFound"
          }
        }
      },
      "put": {
        "summary": "Update project",
        "tags": ["Projects"],
        "security": [{"BearerAuth": []}],
        "parameters": [
          {
            "name": "projectId",
            "in": "path",
            "required": true,
            "schema": {
              "type": "string",
              "format": "uuid"
            }
          }
        ],
        "requestBody": {
          "required": true,
          "content": {
            "application/json": {
              "schema": {
                "type": "object",
                "properties": {
                  "name": {
                    "type": "string",
                    "minLength": 1
                  },
                  "description": {
                    "type": "string"
                  },
                  "visibility": {
                    "type": "string",
                    "enum": ["private", "public", "internal"]
                  },
                  "color": {
                    "type": "string",
                    "pattern": "^#[0-9A-Fa-f]{6}$"
                  },
                  "status": {
                    "type": "string",
                    "enum": ["active", "archived", "completed"]
                  }
                }
              }
            }
          }
        },
        "responses": {
          "200": {
            "description": "Project updated successfully",
            "content": {
              "application/json": {
                "schema": {
                  "$ref": "#/components/schemas/Project"
                }
              }
            }
          }
        }
      },
      "delete": {
        "summary": "Delete project",
        "tags": ["Projects"],
        "security": [{"BearerAuth": []}],
        "parameters": [
          {
            "name": "projectId",
            "in": "path",
            "required": true,
            "schema": {
              "type": "string",
              "format": "uuid"
            }
          }
        ],
        "responses": {
          "204": {
            "description": "Project deleted successfully"
          },
          "404": {
            "$ref": "#/components/responses/NotFound"
          }
        }
      }
    },
    "/projects/{projectId}/tasks": {
      "get": {
        "summary": "List tasks in a project",
        "tags": ["Tasks"],
        "security": [{"BearerAuth": []}],
        "parameters": [
          {
            "name": "projectId",
            "in": "path",
            "required": true,
            "schema": {
              "type": "string",
              "format": "uuid"
            }
          },
          {
            "name": "status",
            "in": "query",
            "schema": {
              "type": "string"
            }
          },
          {
            "name": "assignee_id",
            "in": "query",
            "schema": {
              "type": "string",
              "format": "uuid"
            }
          },
          {
            "name": "priority",
            "in": "query",
            "schema": {
              "type": "string",
              "enum": ["low", "medium", "high", "urgent"]
            }
          }
        ],
        "responses": {
          "200": {
            "description": "Tasks retrieved successfully",
            "content": {
              "application/json": {
                "schema": {
                  "type": "object",
                  "properties": {
                    "tasks": {
                      "type": "array",
                      "items": {
                        "$ref": "#/components/schemas/Task"
                      }
                    },
                    "pagination": {
                      "$ref": "#/components/schemas/Pagination"
                    }
                  }
                }
              }
            }
          }
        }
      },
      "post": {
        "summary": "Create a new task",
        "tags": ["Tasks"],
        "security": [{"BearerAuth": []}],
        "parameters": [
          {
            "name": "projectId",
            "in": "path",
            "required": true,
            "schema": {
              "type": "string",
              "format": "uuid"
            }
          }
        ],
        "requestBody": {
          "required": true,
          "content": {
            "application/json": {
              "schema": {
                "type": "object",
                "required": ["title"],
                "properties": {
                  "title": {
                    "type": "string",
                    "minLength": 1
                  },
                  "description": {
                    "type": "string"
                  },
                  "assignee_id": {
                    "type": "string",
                    "format": "uuid"
                  },
                  "priority": {
                    "type": "string",
                    "enum": ["low", "medium", "high", "urgent"],
                    "default": "medium"
                  },
                  "due_date": {
                    "type": "string",
                    "format": "date-time"
                  },
                  "estimated_hours": {
                    "type": "integer",
                    "minimum": 0
                  },
                  "tags": {
                    "type": "array",
                    "items": {
                      "type": "string"
                    }
                  },
                  "custom_fields": {
                    "type": "object"
                  }
                }
              }
            }
          }
        },
        "responses": {
          "201": {
            "description": "Task created successfully",
            "content": {
              "application/json": {
                "schema": {
                  "$ref": "#/components/schemas/Task"
                }
              }
            }
          }
        }
      }
    },
    "/tasks/{taskId}": {
      "get": {
        "summary": "Get task details",
        "tags": ["Tasks"],
        "security": [{"BearerAuth": []}],
        "parameters": [
          {
            "name": "taskId",
            "in": "path",
            "required": true,
            "schema": {
              "type": "string",
              "format": "uuid"
            }
          }
        ],
        "responses": {
          "200": {
            "description": "Task retrieved successfully",
            "content": {
              "application/json": {
                "schema": {
                  "$ref": "#/components/schemas/Task"
                }
              }
            }
          }
        }
      },
      "put": {
        "summary": "Update task",
        "tags": ["Tasks"],
        "security": [{"BearerAuth": []}],
        "parameters": [
          {
            "name": "taskId",
            "in": "path",
            "required": true,
            "schema": {
              "type": "string",
              "format": "uuid"
            }
          }
        ],
        "requestBody": {
          "required": true,
          "content": {
            "application/json": {
              "schema": {
                "type": "object",
                "properties": {
                  "title": {
                    "type": "string",
                    "minLength": 1
                  },
                  "description": {
                    "type": "string"
                  },
                  "status": {
                    "type": "string"
                  },
                  "assignee_id": {
                    "type": "string",
                    "format": "uuid"
                  },
                  "priority": {
                    "type": "string",
                    "enum": ["low", "medium", "high", "urgent"]
                  },
                  "due_date": {
                    "type": "string",
                    "format": "date-time"
                  },
                  "actual_hours": {
                    "type": "integer",
                    "minimum": 0
                  }
                }
              }
            }
          }
        },
        "responses": {
          "200": {
            "description": "Task updated successfully",
            "content": {
              "application/json": {
                "schema": {
                  "$ref": "#/components/schemas/Task"
                }
              }
            }
          }
        }
      }
    },
    "/tasks/{taskId}/comments": {
      "get": {
        "summary": "List task comments",
        "tags": ["Comments"],
        "security": [{"BearerAuth": []}],
        "parameters": [
          {
            "name": "taskId",
            "in": "path",
            "required": true,
            "schema": {
              "type": "string",
              "format": "uuid"
            }
          }
        ],
        "responses": {
          "200": {
            "description": "Comments retrieved successfully",
            "content": {
              "application/json": {
                "schema": {
                  "type": "array",
                  "items": {
                    "$ref": "#/components/schemas/Comment"
                  }
                }
              }
            }
          }
        }
      },
      "post": {
        "summary": "Add comment to task",
        "tags": ["Comments"],
        "security": [{"BearerAuth": []}],
        "parameters": [
          {
            "name": "taskId",
            "in": "path",
            "required": true,
            "schema": {
              "type": "string",
              "format": "uuid"
            }
          }
        ],
        "requestBody": {
          "required": true,
          "content": {
            "application/json": {
              "schema": {
                "type": "object",
                "required": ["content"],
                "properties": {
                  "content": {
                    "type": "string",
                    "minLength": 1
                  },
                  "parent_comment_id": {
                    "type": "string",
                    "format": "uuid"
                  }
                }
              }
            }
          }
        },
        "responses": {
          "201": {
            "description": "Comment added successfully",
            "content": {
              "application/json": {
                "schema": {
                  "$ref": "#/components/schemas/Comment"
                }
              }
            }
          }
        }
      }
    },
    "/search": {
      "get": {
        "summary": "Global search",
        "tags": ["Search"],
        "security": [{"BearerAuth": []}],
        "parameters": [
          {
            "name": "q",
            "in": "query",
            "required": true,
            "schema": {
              "type": "string",
              "minLength": 1
            },
            "description": "Search query"
          },
          {
            "name": "type",
            "in": "query",
            "schema": {
              "type": "string",
              "enum": ["tasks", "projects", "comments", "files"]
            }
          },
          {
            "name": "project_id",
            "in": "query",
            "schema": {
              "type": "string",
              "format": "uuid"
            }
          },
          {
            "name": "page",
            "in": "query",
            "schema": {
              "type": "integer",
              "minimum": 1,
              "default": 1
            }
          }
        ],
        "responses": {
          "200": {
            "description": "Search results",
            "content": {
              "application/json": {
                "schema": {
                  "type": "object",
                  "properties": {
                    "results": {
                      "type": "array",
                      "items": {
                        "type": "object",
                        "properties": {
                          "type": {
                            "type": "string"
                          },
                          "id": {
                            "type": "string"
                          },
                          "title": {
                            "type": "string"
                          },
                          "content": {
                            "type": "string"
                          },
                          "url": {
                            "type": "string"
                          },
                          "highlight": {
                            "type": "object"
                          }
                        }
                      }
                    },
                    "pagination": {
                      "$ref": "#/components/schemas/Pagination"
                    }
                  }
                }
              }
            }
          }
        }
      }
    },
    "/files/upload": {
      "post": {
        "summary": "Upload file",
        "tags": ["Files"],
        "security": [{"BearerAuth": []}],
        "requestBody": {
          "required": true,
          "content": {
            "multipart/form-data": {
              "schema": {
                "type": "object",
                "required": ["file"],
                "properties": {
                  "file": {
                    "type": "string",
                    "format": "binary"
                  },
                  "task_id": {
                    "type": "string",
                    "format": "uuid"
                  },
                  "project_id": {
                    "type": "string",
                    "format": "uuid"
                  },
                  "description": {
                    "type": "string"
                  }
                }
              }
            }
          }
        },
        "responses": {
          "201": {
            "description": "File uploaded successfully",
            "content": {
              "application/json": {
                "schema": {
                  "$ref": "#/components/schemas/File"
                }
              }
            }
          }
        }
      }
    }
  },
  "components": {
    "schemas": {
      "User": {
        "type": "object",
        "properties": {
          "id": {
            "type": "string",
            "format": "uuid"
          },
          "email": {
            "type": "string",
            "format": "email"
          },
          "name": {
            "type": "string"
          },
          "avatar_url": {
            "type": "string"
          },
          "timezone": {
            "type": "string"
          },
          "created_at": {
            "type": "string",
            "format": "date-time"
          },
          "updated_at": {
            "type": "string",
            "format": "date-time"
          }
        }
      },
      "Project": {
        "type": "object",
        "properties": {
          "id": {
            "type": "string",
            "format": "uuid"
          },
          "name": {
            "type": "string"
          },
          "description": {
            "type": "string"
          },
          "slug": {
            "type": "string"
          },
          "status": {
            "type": "string",
            "enum": ["active", "archived", "completed"]
          },
          "visibility": {
            "type": "string",
            "enum": ["private", "public", "internal"]
          },
          "color": {
            "type": "string"
          },
          "organization_id": {
            "type": "string",
            "format": "uuid"
          },
          "created_by": {
            "type": "string",
            "format": "uuid"
          },
          "created_at": {
            "type": "string",
            "format": "date-time"
          },
          "updated_at": {
            "type": "string",
            "format": "date-time"
          }
        }
      },
      "Task": {
        "type": "object",
        "properties": {
          "id": {
            "type": "string",
            "format": "uuid"
          },
          "project_id": {
            "type": "string",
            "format": "uuid"
          },
          "title": {
            "type": "string"
          },
          "description": {
            "type": "string"
          },
          "status": {
            "type": "string"
          },
          "priority": {
            "type": "string",
            "enum": ["low", "medium", "high", "urgent"]
          },
          "assignee": {
            "$ref": "#/components/schemas/User"
          },
          "reporter": {
            "$ref": "#/components/schemas/User"
          },
          "due_date": {
            "type": "string",
            "format": "date-time"
          },
          "estimated_hours": {
            "type": "integer"
          },
          "actual_hours": {
            "type": "integer"
          },
          "tags": {
            "type": "array",
            "items": {
              "type": "string"
            }
          },
          "custom_fields": {
            "type": "object"
          },
          "created_at": {
            "type": "string",
            "format": "date-time"
          },
          "updated_at": {
            "type": "string",
            "format": "date-time"
          }
        }
      },
      "Comment": {
        "type": "object",
        "properties": {
          "id": {
            "type": "string",
            "format": "uuid"
          },
          "task_id": {
            "type": "string",
            "format": "uuid"
          },
          "author": {
            "$ref": "#/components/schemas/User"
          },
          "content": {
            "type": "string"
          },
          "content_type": {
            "type": "string"
          },
          "parent_comment_id": {
            "type": "string",
            "format": "uuid"
          },
          "is_edited": {
            "type": "boolean"
          },
          "edited_at": {
            "type": "string",
            "format": "date-time"
          },
          "created_at": {
            "type": "string",
            "format": "date-time"
          },
          "updated_at": {
            "type": "string",
            "format": "date-time"
          }
        }
      },
      "File": {
        "type": "object",
        "properties": {
          "id": {
            "type": "string",
            "format": "uuid"
          },
          "filename": {
            "type": "string"
          },
          "original_filename": {
            "type": "string"
          },
          "mime_type": {
            "type": "string"
          },
          "size_bytes": {
            "type": "integer"
          },
          "uploaded_by": {
            "$ref": "#/components/schemas/User"
          },
          "description": {
            "type": "string"
          },
          "created_at": {
            "type": "string",
            "format": "date-time"
          }
        }
      },
      "Pagination": {
        "type": "object",
        "properties": {
          "page": {
            "type": "integer"
          },
          "limit": {
            "type": "integer"
          },
          "total": {
            "type": "integer"
          },
          "total_pages": {
            "type": "integer"
          },
          "has_next": {
            "type": "boolean"
          },
          "has_prev": {
            "type": "boolean"
          }
        }
      }
    },
    "responses": {
      "BadRequest": {
        "description": "Bad request",
        "content": {
          "application/json": {
            "schema": {
              "type": "object",
              "properties": {
                "error": {
                  "type": "string"
                },
                "message": {
                  "type": "string"
                },
                "details": {
                  "type": "object"
                }
              }
            }
          }
        }
      },
      "Unauthorized": {
        "description": "Unauthorized",
        "content": {
          "application/json": {
            "schema": {
              "type": "object",
              "properties": {
                "error": {
                  "type": "string"
                },
                "message": {
                  "type": "string"
                }
              }
            }
          }
        }
      },
      "NotFound": {
        "description": "Resource not found",
        "content": {
          "application/json": {
            "schema": {
              "type": "object",
              "properties": {
                "error": {
                  "type": "string"
                },
                "message": {
                  "type": "string"
                }
              }
            }
          }
        }
      },
      "Conflict": {
        "description": "Resource conflict",
        "content": {
          "application/json": {
            "schema": {
              "type": "object",
              "properties": {
                "error": {
                  "type": "string"
                },
                "message": {
                  "type": "string"
                }
              }
            }
          }
        }
      }
    },
    "securitySchemes": {
      "BearerAuth": {
        "type": "http",
        "scheme": "bearer",
        "bearerFormat": "JWT"
      }
    }
  }
}